arcor2_build_data/VERSION
arcor2_build_data/__init__.py
arcor2_build_data/exceptions.py
arcor2_build_data/py.typed
arcor2_build_data-1.1.0.dist-info/METADATA
arcor2_build_data-1.1.0.dist-info/WHEEL
arcor2_build_data-1.1.0.dist-info/namespace_packages.txt
arcor2_build_data-1.1.0.dist-info/top_level.txt
arcor2_build_data-1.1.0.dist-info/RECORD
